README.rst
setup.py
test/__init__.py
test/conftest.py
test/test_agents.py
test/test_cache.py
test/test_codec.py
test/test_pool.py
test/test_wallet.py
von_agent/__init__.py
von_agent/cache.py
von_agent/codec.py
von_agent/error.py
von_agent/nodepool.py
von_agent/tails.py
von_agent/util.py
von_agent/validate_config.py
von_agent/wallet.py
von_agent.egg-info/PKG-INFO
von_agent.egg-info/SOURCES.txt
von_agent.egg-info/dependency_links.txt
von_agent.egg-info/requires.txt
von_agent.egg-info/top_level.txt
von_agent/agent/__init__.py
von_agent/agent/base.py
von_agent/agent/demo.py
von_agent/agent/holder_prover.py
von_agent/agent/issuer.py
von_agent/agent/origin.py
von_agent/agent/registrar.py
von_agent/agent/verifier.py