Metadata-Version: 1.2
Name: von-agent
Version: 1.5.1
Summary: VON agents
Home-page: https://github.com/PSPC-SPAC-buyandsell/von_agent
Author: PSPS-SPAC
Author-email: stephen.klump@becker-carroll.com
License: Apache Software License
Download-URL: https://github.com/PSPC-SPAC-buyandsell/von_agent/archive/1.5.1.tar.gz
Keywords: VON,SRI,agent,The Org Book,indy
Platform: UNKNOWN
Classifier: Development Status :: 3 - Alpha
Classifier: Intended Audience :: Developers
Classifier: Topic :: Software Development
Classifier: License :: OSI Approved :: Apache Software License
Classifier: Programming Language :: Python :: 3.5
Requires-Python: >=3.5
